{
  "memberInfo": {
    "id": 999,
    "firstName": "Azamat",
    "lastName": "Mambetaliev",
    "height": 178,
    "weight": 70,
    "departament": "Information Technology",
    "city": "Tokmok",
    "status": "student",
    "organization": "IUCA",
    "mentees_id": [ // array
      1056,
      1097,
      1112,
      1102,
      1009,
      34
    ],
    "educations": { // nested structure
      "school" : "High school №3",
      "college" : "Tech College in Tokmok",
      "university" : "IUCA",
      "clubs" : ["IUCA_TV", "Neobis_clubs(perhaps)"]
    }
  }
}
